dupfilter/__init__.py
dupfilter/filters/__init__.py
dupfilter/filters/file.py
dupfilter/filters/memory.py
dupfilter/filters/redis/__init__.py
dupfilter/filters/redis/bloomfilter.py
dupfilter/filters/redis/setfilter.py
dupfilter/filters/redis/sortedsetfilter.py
dupfilter/filters/redis/stringfilter.py
dupfilter/filters/sql/__init__.py
dupfilter/filters/sql/mysql.py
dupfilter/filters/sql/oracle.py
dupfilter/filters/sql/sqlite.py
dupfilter/utils/__init__.py
dupfilter-0.0.5.dist-info/LICENSE
dupfilter-0.0.5.dist-info/METADATA
dupfilter-0.0.5.dist-info/WHEEL
dupfilter-0.0.5.dist-info/top_level.txt
dupfilter-0.0.5.dist-info/RECORD
