Metadata-Version: 2.1
Name: dupfilter
Version: 0.0.5
Summary: 去重过滤器,提供常见的去重方案，开发便捷、性能极高。
Home-page: https://github.com/kusen-alpha/dupfilter
Author: kusen
Author-email: 1194542196@qq.com
License: MIT
Project-URL: Bug Tracker, https://github.com/kusen-alpha/dupfilter/issues
Project-URL: Documentation, https://github.com/kusen-alpha/dupfilter/blob/master/README.md
Project-URL: Source Code, https://github.com/kusen-alpha/dupfilter
Platform: any
Classifier: Programming Language :: Python :: 3
Classifier: License :: OSI Approved :: MIT License
Classifier: Operating System :: OS Independent
License-File: LICENSE
Requires-Dist: cachetools
